README.md
setup.py
baidubce/__init__.py
baidubce/bce_base_client.py
baidubce/bce_client_configuration.py
baidubce/bce_response.py
baidubce/exception.py
baidubce/protocol.py
baidubce/region.py
baidubce/retry_policy.py
baidubce/utils.py
baidubce/auth/__init__.py
baidubce/auth/bce_credentials.py
baidubce/auth/bce_v1_signer.py
baidubce/http/__init__.py
baidubce/http/bce_http_client.py
baidubce/http/handler.py
baidubce/http/http_content_types.py
baidubce/http/http_headers.py
baidubce/http/http_methods.py
baidubce/services/__init__.py
baidubce/services/bmr/__init__.py
baidubce/services/bmr/bmr_client.py
baidubce/services/bos/__init__.py
baidubce/services/bos/bos_client.py
baidubce/services/bos/bos_handler.py
baidubce/services/bos/canned_acl.py
baidubce/services/bos/storage_class.py
baidubce/services/media/__init__.py
baidubce/services/media/media_client.py
baidubce/services/sms/__init__.py
baidubce/services/sms/sms_client.py
baidubce/services/sts/__init__.py
baidubce/services/sts/sts_client.py
bce_sdk.egg-info/PKG-INFO
bce_sdk.egg-info/SOURCES.txt
bce_sdk.egg-info/dependency_links.txt
bce_sdk.egg-info/top_level.txt