Metadata-Version: 1.0
Name: bce-sdk
Version: 0.8.16
Summary: BCE SDK for python
Home-page: http://bce.baidu.com
Author: UNKNOWN
Author-email: UNKNOWN
License: Apache License 2.0
Platform: UNKNOWN
